m_lib-3.1.2-py2.7-nspkg.pth
m_lib/flog.py
m_lib/m_path.py
m_lib/m_shutil.py
m_lib/mcrypt.py
m_lib/md5wrapper.py
m_lib/metaclasses.py
m_lib/opdate.py
m_lib/opstring.py
m_lib/tty_menu.py
m_lib/clock/__init__.py
m_lib/clock/mkclock.py
m_lib/clock/tstclock.py
m_lib/flad/__init__.py
m_lib/flad/flad.py
m_lib/flad/fladc.py
m_lib/flad/fladm.py
m_lib/flad/fladw.py
m_lib/hash/MKhash.py
m_lib/hash/ZODBhash.py
m_lib/hash/__init__.py
m_lib/hash/zshelve.py
m_lib/lazy/__init__.py
m_lib/lazy/dict.py
m_lib/lazy/imports.py
m_lib/net/__init__.py
m_lib/net/ftp/__init__.py
m_lib/net/ftp/ftpparse.py
m_lib/net/ftp/ftpscan.py
m_lib/net/www/__init__.py
m_lib/net/www/dtml.py
m_lib/net/www/html.py
m_lib/net/www/serverpush.py
m_lib/net/www/url_lib.py
m_lib/net/www/util.py
m_lib/net/www/xml.py
m_lib/pbar/__init__.py
m_lib/pbar/tty_pbar.py
m_lib/rus/__init__.py
m_lib/rus/lat2rus.py
m_lib/rus/rus2lat.py
m_lib-3.1.2.dist-info/METADATA
m_lib-3.1.2.dist-info/RECORD
m_lib-3.1.2.dist-info/WHEEL
m_lib-3.1.2.dist-info/namespace_packages.txt
m_lib-3.1.2.dist-info/top_level.txt
