Metadata-Version: 2.1
Name: m-lib
Version: 3.1.2
Summary: Broytman Library for Python
Home-page: https://phdru.name/Software/Python/#m_lib
Author: Oleg Broytman
Author-email: phd@phdru.name
License: GPL
Project-URL: Download, https://pypi.org/project/m_lib/
Project-URL: Git repo, https://git.phdru.name/m_lib.git/
Project-URL: Homepage, https://phdru.name/Software/Python/#m_lib
Platform: Any
Classifier: Development Status :: 5 - Production/Stable
Classifier: Intended Audience :: Developers
Classifier: License :: OSI Approved :: GNU General Public License (GPL)
Classifier: Operating System :: OS Independent
Classifier: Programming Language :: Python :: 2
Classifier: Programming Language :: Python :: 2.7
Classifier: Programming Language :: Python :: 3
Classifier: Programming Language :: Python :: 3.4
Classifier: Programming Language :: Python :: 3.5
Classifier: Programming Language :: Python :: 3.6
Classifier: Programming Language :: Python :: 3.7
Classifier: Programming Language :: Python :: 3.8
Classifier: Programming Language :: Python :: 3.9
Classifier: Programming Language :: Python :: 3.10
Classifier: Programming Language :: Python :: 3.11
Classifier: Programming Language :: Python :: 3.12
Classifier: Programming Language :: Python :: 3.13
Classifier: Programming Language :: Python :: 3.14
Classifier: Topic :: Software Development :: Libraries
Classifier: Topic :: Software Development :: Libraries :: Python Modules
Requires-Python: >=2.7, !=3.0.*, !=3.1.*, !=3.2.*, !=3.3.*
Provides-Extra: Metakit
Provides-Extra: ZODB
Provides-Extra: mx
Provides-Extra: Metakit
Requires-Dist: Mk4py; extra == 'Metakit'
Provides-Extra: ZODB
Requires-Dist: ZODB; extra == 'ZODB'
Provides-Extra: mx
Requires-Dist: mx.DateTime; extra == 'mx'
Requires-Dist: mx.Misc; extra == 'mx'
